{
    "NUR": {
        "branch": "master",
        "description": "Nix User Repository: User contributed nix packages [maintainer=@Mic92]",
        "homepage": "",
        "owner": "nix-community",
        "repo": "NUR",
        "rev": "e87fdd4774fbd3cf8ea0540dc0a6088289c9c128",
        "sha256": "123fix78jb39y1b6j172k9arcqgksnfp6fihp0fvbi37hwpywkyc",
        "type": "tarball",
        "url": "https://github.com/nix-community/NUR/archive/e87fdd4774fbd3cf8ea0540dc0a6088289c9c128.tar.gz",
        "url_template": "https://github.com/<owner>/<repo>/archive/<rev>.tar.gz"
    },
    "agenix": {
        "branch": "main",
        "description": "age-encrypted secrets for NixOS",
        "homepage": "",
        "owner": "ryantm",
        "repo": "agenix",
        "rev": "764c975e74bce2f89a5106b68ec48e2b586f893c",
        "sha256": "0lzr43pcfbhk0qmac4g2giglyvq1rkgcwh88sfi5l79n48a5fhr4",
        "type": "tarball",
        "url": "https://github.com/ryantm/agenix/archive/764c975e74bce2f89a5106b68ec48e2b586f893c.tar.gz",
        "url_template": "https://github.com/<owner>/<repo>/archive/<rev>.tar.gz"
    },
    "home-manager": {
        "branch": "master",
        "description": "Manage a user environment using Nix  [maintainer=@rycee] ",
        "homepage": "https://rycee.gitlab.io/home-manager/",
        "owner": "nix-community",
        "repo": "home-manager",
        "rev": "cfab869fcebc56710be6ec3aca76036b25c04a0d",
        "sha256": "0a5zklb8nkbp36j1qnxk4fmbpzssg8swllfijf1fqpgsqcg9bp3x",
        "type": "tarball",
        "url": "https://github.com/nix-community/home-manager/archive/cfab869fcebc56710be6ec3aca76036b25c04a0d.tar.gz",
        "url_template": "https://github.com/<owner>/<repo>/archive/<rev>.tar.gz"
    },
    "nixos-hardware": {
        "branch": "master",
        "description": "A collection of NixOS modules covering hardware quirks.",
        "homepage": "",
        "owner": "NixOS",
        "repo": "nixos-hardware",
        "rev": "feceb4d24f582817d8f6e737cd40af9e162dee05",
        "sha256": "1q92jq6xf5b1pshai9j72cj17r0ah3fhrx669h3vc58rj7xvgiw7",
        "type": "tarball",
        "url": "https://github.com/NixOS/nixos-hardware/archive/feceb4d24f582817d8f6e737cd40af9e162dee05.tar.gz",
        "url_template": "https://github.com/<owner>/<repo>/archive/<rev>.tar.gz"
    },
    "nixpkgs": {
        "branch": "nixos-unstable",
        "description": "Nix Packages collection",
        "homepage": null,
        "owner": "NixOS",
        "repo": "nixpkgs",
        "rev": "710fed5a2483f945b14f4a58af2cd3676b42d8c8",
        "sha256": "1xhbkgb9rzh2b0rbyhcygvc6216g9qbqyjkkgrhwfclsx06sfach",
        "type": "tarball",
        "url": "https://github.com/NixOS/nixpkgs/archive/710fed5a2483f945b14f4a58af2cd3676b42d8c8.tar.gz",
        "url_template": "https://github.com/<owner>/<repo>/archive/<rev>.tar.gz"
    }
}
