{
    "NUR": {
        "branch": "master",
        "description": "Nix User Repository: User contributed nix packages [maintainer=@Mic92]",
        "homepage": "",
        "owner": "nix-community",
        "repo": "NUR",
        "rev": "8bf7dd8538ed9bd7a657bd1f59e8540fe5446306",
        "sha256": "0p3qkx09xrpvv16pqcxb927iyhg32yvr3i5gk75a8rnkgdkdv7g8",
        "type": "tarball",
        "url": "https://github.com/nix-community/NUR/archive/8bf7dd8538ed9bd7a657bd1f59e8540fe5446306.tar.gz",
        "url_template": "https://github.com/<owner>/<repo>/archive/<rev>.tar.gz"
    },
    "home-manager": {
        "branch": "master",
        "description": "Manage a user environment using Nix  [maintainer=@rycee] ",
        "homepage": "https://rycee.gitlab.io/home-manager/",
        "owner": "nix-community",
        "repo": "home-manager",
        "rev": "c59f0eac51da91c6989fd13a68e156f63c0e60b6",
        "sha256": "05msmzfa45l9sr9ngd2cfxw66kw0x76d68gp29v5ilrakf8nc90w",
        "type": "tarball",
        "url": "https://github.com/nix-community/home-manager/archive/c59f0eac51da91c6989fd13a68e156f63c0e60b6.tar.gz",
        "url_template": "https://github.com/<owner>/<repo>/archive/<rev>.tar.gz"
    },
    "nixos-hardware": {
        "branch": "master",
        "description": "A collection of NixOS modules covering hardware quirks.",
        "homepage": "",
        "owner": "NixOS",
        "repo": "nixos-hardware",
        "rev": "b7ac0a56029e4f9e6743b9993037a5aaafd57103",
        "sha256": "0yaw8q5kj34wnb1hzm0zchb43vnqn1llx5karmdx1hhrahh6acln",
        "type": "tarball",
        "url": "https://github.com/NixOS/nixos-hardware/archive/b7ac0a56029e4f9e6743b9993037a5aaafd57103.tar.gz",
        "url_template": "https://github.com/<owner>/<repo>/archive/<rev>.tar.gz"
    },
    "nixpkgs": {
        "branch": "nixos-unstable",
        "description": "Nix Packages collection",
        "homepage": null,
        "owner": "NixOS",
        "repo": "nixpkgs",
        "rev": "1b1f50645af2a70dc93eae18bfd88d330bfbcf7f",
        "sha256": "08vs2pqldj7wi24xkdcahwsn9knrp2ygjkdqnb3727xnzfbiji9g",
        "type": "tarball",
        "url": "https://github.com/NixOS/nixpkgs/archive/1b1f50645af2a70dc93eae18bfd88d330bfbcf7f.tar.gz",
        "url_template": "https://github.com/<owner>/<repo>/archive/<rev>.tar.gz"
    },
    "nixpkgs-master": {
        "branch": "master",
        "description": "Nix Packages collection",
        "homepage": "",
        "owner": "nixos",
        "repo": "nixpkgs",
        "rev": "789f31e77367ec9a4fbc95f0d8a78b90e82ee6b9",
        "sha256": "0dfci955nh62qrlgxmgw5lbl84l71lz02251apfawz4hvnn7ang2",
        "type": "tarball",
        "url": "https://github.com/nixos/nixpkgs/archive/789f31e77367ec9a4fbc95f0d8a78b90e82ee6b9.tar.gz",
        "url_template": "https://github.com/<owner>/<repo>/archive/<rev>.tar.gz"
    },
    "nixpkgs-stable": {
        "branch": "nixos-22.11",
        "description": "Nix Packages collection",
        "homepage": null,
        "owner": "NixOS",
        "repo": "nixpkgs",
        "rev": "ab1254087f4cdf4af74b552d7fc95175d9bdbb49",
        "sha256": "0n8fv6072mcb923rr7d7l7sx1acblfpkrpv7fn2x886gdbr1rb6s",
        "type": "tarball",
        "url": "https://github.com/NixOS/nixpkgs/archive/ab1254087f4cdf4af74b552d7fc95175d9bdbb49.tar.gz",
        "url_template": "https://github.com/<owner>/<repo>/archive/<rev>.tar.gz"
    }
}
