{
    "NUR": {
        "branch": "master",
        "description": "Nix User Repository: User contributed nix packages [maintainer=@Mic92]",
        "homepage": "",
        "owner": "nix-community",
        "repo": "NUR",
        "rev": "e8f0c4343d2c497ec3bf268d19b4240bd5b8d883",
        "sha256": "0ny5r86dss3g3b09j3k0rfx5d40hr9cmj0ma5l84rlhr9x37b2xi",
        "type": "tarball",
        "url": "https://github.com/nix-community/NUR/archive/e8f0c4343d2c497ec3bf268d19b4240bd5b8d883.tar.gz",
        "url_template": "https://github.com/<owner>/<repo>/archive/<rev>.tar.gz"
    },
    "devshell": {
        "branch": "master",
        "description": "Per project developer environments",
        "homepage": "",
        "owner": "numtide",
        "repo": "devshell",
        "rev": "5d2ad08eb7cb0cf1f73b6f6e0ccfd2508a4995d7",
        "sha256": "16fybrggp1xp3y3slaapc61sb2b5llkgmwk81770f36vjdwhf6lh",
        "type": "tarball",
        "url": "https://github.com/numtide/devshell/archive/5d2ad08eb7cb0cf1f73b6f6e0ccfd2508a4995d7.tar.gz",
        "url_template": "https://github.com/<owner>/<repo>/archive/<rev>.tar.gz"
    },
    "home-manager": {
        "branch": "master",
        "description": "Manage a user environment using Nix  [maintainer=@rycee] ",
        "homepage": "https://rycee.gitlab.io/home-manager/",
        "owner": "nix-community",
        "repo": "home-manager",
        "rev": "56f5f41ed42f7d476a7c79fa8ec71f5605487abf",
        "sha256": "15kdakm06xrx2gkk17a79661asm83b3ap7y9dilqxap0sp2bflff",
        "type": "tarball",
        "url": "https://github.com/nix-community/home-manager/archive/56f5f41ed42f7d476a7c79fa8ec71f5605487abf.tar.gz",
        "url_template": "https://github.com/<owner>/<repo>/archive/<rev>.tar.gz"
    },
    "nixos-hardware": {
        "branch": "master",
        "description": "A collection of NixOS modules covering hardware quirks.",
        "homepage": "",
        "owner": "NixOS",
        "repo": "nixos-hardware",
        "rev": "7c00c8b5cab5dedb6519eabba7ca6d069e2dfdae",
        "sha256": "0d19h1zfqr1l7ls7bp75w9fpb1n810rbvphw5kzvk29yyb624dg5",
        "type": "tarball",
        "url": "https://github.com/NixOS/nixos-hardware/archive/7c00c8b5cab5dedb6519eabba7ca6d069e2dfdae.tar.gz",
        "url_template": "https://github.com/<owner>/<repo>/archive/<rev>.tar.gz"
    },
    "nixpkgs": {
        "branch": "master",
        "description": "Nix Packages collection",
        "homepage": null,
        "owner": "NixOS",
        "repo": "nixpkgs",
        "rev": "ca44268569be4eb348b24bc0705e0482b9ea87a1",
        "sha256": "14s2z140q3646wdki47421g45d2wx8wd4x9382na7s73c8swi7yc",
        "type": "tarball",
        "url": "https://github.com/NixOS/nixpkgs/archive/ca44268569be4eb348b24bc0705e0482b9ea87a1.tar.gz",
        "url_template": "https://github.com/<owner>/<repo>/archive/<rev>.tar.gz"
    }
}
