{
    "NUR": {
        "branch": "master",
        "description": "Nix User Repository: User contributed nix packages [maintainer=@Mic92]",
        "homepage": "",
        "owner": "nix-community",
        "repo": "NUR",
        "rev": "527411663d36cfa92d738ec0fee99e4e5e7ed0ba",
        "sha256": "199qrcw6da1s2rj89dac1br5li1rpc7vxkr4xw7apbym634b7mhc",
        "type": "tarball",
        "url": "https://github.com/nix-community/NUR/archive/527411663d36cfa92d738ec0fee99e4e5e7ed0ba.tar.gz",
        "url_template": "https://github.com/<owner>/<repo>/archive/<rev>.tar.gz"
    },
    "home-manager": {
        "branch": "master",
        "description": "Manage a user environment using Nix  [maintainer=@rycee] ",
        "homepage": "https://rycee.gitlab.io/home-manager/",
        "owner": "nix-community",
        "repo": "home-manager",
        "rev": "827636c619ce0d8178ddc08ab86ee92b50f2e5b4",
        "sha256": "0imqxlj40fabg7iifqqa5d91is842124qpflb8l36xpcjgfs4q4p",
        "type": "tarball",
        "url": "https://github.com/nix-community/home-manager/archive/827636c619ce0d8178ddc08ab86ee92b50f2e5b4.tar.gz",
        "url_template": "https://github.com/<owner>/<repo>/archive/<rev>.tar.gz"
    },
    "nixos-hardware": {
        "branch": "master",
        "description": "A collection of NixOS modules covering hardware quirks.",
        "homepage": "",
        "owner": "NixOS",
        "repo": "nixos-hardware",
        "rev": "f7540d6c27704ec0fe56ecc8b2a9b663181850b0",
        "sha256": "1rr470h5frly4a6wwpm1pmfgv57v5f7zwlc73sdx93ms7pc050lf",
        "type": "tarball",
        "url": "https://github.com/NixOS/nixos-hardware/archive/f7540d6c27704ec0fe56ecc8b2a9b663181850b0.tar.gz",
        "url_template": "https://github.com/<owner>/<repo>/archive/<rev>.tar.gz"
    },
    "nixpkgs": {
        "branch": "nixos-unstable",
        "description": "Nix Packages collection",
        "homepage": null,
        "owner": "NixOS",
        "repo": "nixpkgs",
        "rev": "1fe6ed37fd9beb92afe90671c0c2a662a03463dd",
        "sha256": "1daa0y3p17shn9gibr321vx8vija6bfsb5zd7h4pxdbbwjkfq8n2",
        "type": "tarball",
        "url": "https://github.com/NixOS/nixpkgs/archive/1fe6ed37fd9beb92afe90671c0c2a662a03463dd.tar.gz",
        "url_template": "https://github.com/<owner>/<repo>/archive/<rev>.tar.gz"
    }
}
