{
    "NUR": {
        "branch": "master",
        "description": "Nix User Repository: User contributed nix packages [maintainer=@Mic92]",
        "homepage": "",
        "owner": "nix-community",
        "repo": "NUR",
        "rev": "9e292dcf055f77df5f7ea0f5711ce2dcdc23dc97",
        "sha256": "1xsbqg9cmqgmd5lqz0axphfddg9nfwl9igag2vrssyzw6s282g1l",
        "type": "tarball",
        "url": "https://github.com/nix-community/NUR/archive/9e292dcf055f77df5f7ea0f5711ce2dcdc23dc97.tar.gz",
        "url_template": "https://github.com/<owner>/<repo>/archive/<rev>.tar.gz"
    },
    "home-manager": {
        "branch": "master",
        "description": "Manage a user environment using Nix  [maintainer=@rycee] ",
        "homepage": "https://rycee.gitlab.io/home-manager/",
        "owner": "nix-community",
        "repo": "home-manager",
        "rev": "839645caf35b7004d3422fbdba6db1d762a410d0",
        "sha256": "199q5nwr88by27aqdlj6b0ysxdrf2gaf8hafrpjp8wdpq9csiazs",
        "type": "tarball",
        "url": "https://github.com/nix-community/home-manager/archive/839645caf35b7004d3422fbdba6db1d762a410d0.tar.gz",
        "url_template": "https://github.com/<owner>/<repo>/archive/<rev>.tar.gz"
    },
    "nixos-hardware": {
        "branch": "master",
        "description": "A collection of NixOS modules covering hardware quirks.",
        "homepage": "",
        "owner": "NixOS",
        "repo": "nixos-hardware",
        "rev": "241d8300b2746c1db715eaf8d64748990cd0bb7a",
        "sha256": "1wvznygllpbn0czvx5b45cm4spmz31iiyanmmnmrbmhvx8lpd5hv",
        "type": "tarball",
        "url": "https://github.com/NixOS/nixos-hardware/archive/241d8300b2746c1db715eaf8d64748990cd0bb7a.tar.gz",
        "url_template": "https://github.com/<owner>/<repo>/archive/<rev>.tar.gz"
    },
    "nixpkgs": {
        "branch": "master",
        "description": "Nix Packages collection",
        "homepage": null,
        "owner": "NixOS",
        "repo": "nixpkgs",
        "rev": "abd57b544e59b54a24f930899329508aa3ec3b17",
        "sha256": "0d6f0d4j5jhnvwdbsgddc62qls7yw1l916mmfq5an9pz5ykc9nwy",
        "type": "tarball",
        "url": "https://github.com/NixOS/nixpkgs/archive/abd57b544e59b54a24f930899329508aa3ec3b17.tar.gz",
        "url_template": "https://github.com/<owner>/<repo>/archive/<rev>.tar.gz"
    }
}
