{
    "NUR": {
        "branch": "master",
        "description": "Nix User Repository: User contributed nix packages [maintainer=@Mic92]",
        "homepage": "",
        "owner": "nix-community",
        "repo": "NUR",
        "rev": "bce93c1b8ec55a13ccab172d97f87909f20adb47",
        "sha256": "0jvzdyh8ibl5ag3ni8dbhgigh2ci9np12qhzar65miywkw41mzpi",
        "type": "tarball",
        "url": "https://github.com/nix-community/NUR/archive/bce93c1b8ec55a13ccab172d97f87909f20adb47.tar.gz",
        "url_template": "https://github.com/<owner>/<repo>/archive/<rev>.tar.gz"
    },
    "home-manager": {
        "branch": "master",
        "description": "Manage a user environment using Nix  [maintainer=@rycee] ",
        "homepage": "https://rycee.gitlab.io/home-manager/",
        "owner": "nix-community",
        "repo": "home-manager",
        "rev": "60c6bfe322944d04bb38e76b64effcbd01258824",
        "sha256": "1kcpj816cfkn8nxjbhracpryzwcryhfap8n1dmb23h6ia2629jmr",
        "type": "tarball",
        "url": "https://github.com/nix-community/home-manager/archive/60c6bfe322944d04bb38e76b64effcbd01258824.tar.gz",
        "url_template": "https://github.com/<owner>/<repo>/archive/<rev>.tar.gz"
    },
    "nixos-hardware": {
        "branch": "master",
        "description": "A collection of NixOS modules covering hardware quirks.",
        "homepage": "",
        "owner": "NixOS",
        "repo": "nixos-hardware",
        "rev": "1fec8fda86dac5701146c77d5f8a414b14ed1ff6",
        "sha256": "18z2v5id3sad22f4nk8yjpablk9c693nwl5vix2n06h6s3kfmr10",
        "type": "tarball",
        "url": "https://github.com/NixOS/nixos-hardware/archive/1fec8fda86dac5701146c77d5f8a414b14ed1ff6.tar.gz",
        "url_template": "https://github.com/<owner>/<repo>/archive/<rev>.tar.gz"
    },
    "nixpkgs": {
        "branch": "nixos-unstable",
        "description": "Nix Packages collection",
        "homepage": null,
        "owner": "NixOS",
        "repo": "nixpkgs",
        "rev": "5f326e2a403e1cebaec378e72ceaf5725983376d",
        "sha256": "01lfac9zr1sx0whkd25d3jww3y3wcbyv4dck684k774p5gfx1wjy",
        "type": "tarball",
        "url": "https://github.com/NixOS/nixpkgs/archive/5f326e2a403e1cebaec378e72ceaf5725983376d.tar.gz",
        "url_template": "https://github.com/<owner>/<repo>/archive/<rev>.tar.gz"
    }
}
