{
    "NUR": {
        "branch": "master",
        "description": "Nix User Repository: User contributed nix packages [maintainer=@Mic92]",
        "homepage": "",
        "owner": "nix-community",
        "repo": "NUR",
        "rev": "63ce681a0abe4e85449ef82a2a1b1bb73d0c3a5f",
        "sha256": "03plphn1z418s7m5ykxw1zmrpz3m6wqppxknvbzsv41vj4v0sh42",
        "type": "tarball",
        "url": "https://github.com/nix-community/NUR/archive/63ce681a0abe4e85449ef82a2a1b1bb73d0c3a5f.tar.gz",
        "url_template": "https://github.com/<owner>/<repo>/archive/<rev>.tar.gz"
    },
    "home-manager": {
        "branch": "master",
        "description": "Manage a user environment using Nix  [maintainer=@rycee] ",
        "homepage": "https://rycee.gitlab.io/home-manager/",
        "owner": "nix-community",
        "repo": "home-manager",
        "rev": "579f2e8bebb954a103a96b905c27b10f15ef38c7",
        "sha256": "1qym3jxd30cvqpdqh6ppmv7yl1x47yyadziwllbdpa5187mbc1ck",
        "type": "tarball",
        "url": "https://github.com/nix-community/home-manager/archive/579f2e8bebb954a103a96b905c27b10f15ef38c7.tar.gz",
        "url_template": "https://github.com/<owner>/<repo>/archive/<rev>.tar.gz"
    },
    "nixos-hardware": {
        "branch": "master",
        "description": "A collection of NixOS modules covering hardware quirks.",
        "homepage": "",
        "owner": "NixOS",
        "repo": "nixos-hardware",
        "rev": "aad66afc1cac4a654223f6ba326899c731e57441",
        "sha256": "1cj4xnyqll20pjwnwkknbzsdvm8c59x2p4cxaggna7510zs5h53b",
        "type": "tarball",
        "url": "https://github.com/NixOS/nixos-hardware/archive/aad66afc1cac4a654223f6ba326899c731e57441.tar.gz",
        "url_template": "https://github.com/<owner>/<repo>/archive/<rev>.tar.gz"
    },
    "nixpkgs": {
        "branch": "nixos-unstable",
        "description": "Nix Packages collection",
        "homepage": null,
        "owner": "NixOS",
        "repo": "nixpkgs",
        "rev": "73369f8d0864854d1acfa7f1e6217f7d6b6e3fa1",
        "sha256": "11z477rs1s2lhpw9h45npby86nqs7rqhi45ikh742ssxfwla52j1",
        "type": "tarball",
        "url": "https://github.com/NixOS/nixpkgs/archive/73369f8d0864854d1acfa7f1e6217f7d6b6e3fa1.tar.gz",
        "url_template": "https://github.com/<owner>/<repo>/archive/<rev>.tar.gz"
    }
}
