{
    "NUR": {
        "branch": "master",
        "description": "Nix User Repository: User contributed nix packages [maintainer=@Mic92]",
        "homepage": "",
        "owner": "nix-community",
        "repo": "NUR",
        "rev": "ad3161a876ddc23b22135153909b48df40682e7b",
        "sha256": "0zjigj4i7wanpnp2l06r9lffpwzx3k3w0gh00ylx2lkgh8943wny",
        "type": "tarball",
        "url": "https://github.com/nix-community/NUR/archive/ad3161a876ddc23b22135153909b48df40682e7b.tar.gz",
        "url_template": "https://github.com/<owner>/<repo>/archive/<rev>.tar.gz"
    },
    "home-manager": {
        "branch": "master",
        "description": "Manage a user environment using Nix  [maintainer=@rycee] ",
        "homepage": "https://rycee.gitlab.io/home-manager/",
        "owner": "nix-community",
        "repo": "home-manager",
        "rev": "06ee8ec8dfc4554c374052cd7b7083765748af99",
        "sha256": "1g2d6f4mhj71drnyh8wa7358f36vfw7yxdfq9cjwff1zaa9lp142",
        "type": "tarball",
        "url": "https://github.com/nix-community/home-manager/archive/06ee8ec8dfc4554c374052cd7b7083765748af99.tar.gz",
        "url_template": "https://github.com/<owner>/<repo>/archive/<rev>.tar.gz"
    },
    "nix": {
        "branch": "master",
        "description": "Nix, the purely functional package manager",
        "homepage": "https://nixos.org/nix/",
        "owner": "NixOS",
        "repo": "nix",
        "rev": "9cf991f421b20a2c753df1f93730ddc8ddf7af6c",
        "sha256": "0c2hqigjg8b83v4a873xs95b9pkdvj9ngml6ghynkkv58ggwbcdf",
        "type": "tarball",
        "url": "https://github.com/NixOS/nix/archive/9cf991f421b20a2c753df1f93730ddc8ddf7af6c.tar.gz",
        "url_template": "https://github.com/<owner>/<repo>/archive/<rev>.tar.gz"
    },
    "nixos-hardware": {
        "branch": "master",
        "description": "A collection of NixOS modules covering hardware quirks.",
        "homepage": "",
        "owner": "NixOS",
        "repo": "nixos-hardware",
        "rev": "41775780a0b6b32b3d32dcc32bb9bc6df809062d",
        "sha256": "0121bmdga42zkn4y3wsy71b5lglzn180q7vmxaprqp5lvr27v8ik",
        "type": "tarball",
        "url": "https://github.com/NixOS/nixos-hardware/archive/41775780a0b6b32b3d32dcc32bb9bc6df809062d.tar.gz",
        "url_template": "https://github.com/<owner>/<repo>/archive/<rev>.tar.gz"
    },
    "nixpkgs": {
        "branch": "nixos-unstable",
        "description": "Nix Packages collection",
        "homepage": null,
        "owner": "NixOS",
        "repo": "nixpkgs",
        "rev": "87807e64a5ef5206b745a40af118c7be8db73681",
        "sha256": "056jv0m6x3q95ndj8mrwsy90s4imv34dl1lri9qyjrvl8r33kzzy",
        "type": "tarball",
        "url": "https://github.com/NixOS/nixpkgs/archive/87807e64a5ef5206b745a40af118c7be8db73681.tar.gz",
        "url_template": "https://github.com/<owner>/<repo>/archive/<rev>.tar.gz"
    }
}
