{
    "aagl-gtk-on-nix": {
        "branch": "main",
        "description": "Run an-anime-game-launcher GTK version on Nix/NixOS!",
        "homepage": null,
        "owner": "ezKEa",
        "repo": "aagl-gtk-on-nix",
        "rev": "fb1400959763420d1d1fb9db289a45b4d4649a48",
        "sha256": "18mndsbszb3rbfpxh6k6wwilp07fj7liz3s945iww58jz6cvwx1i",
        "type": "tarball",
        "url": "https://github.com/ezKEa/aagl-gtk-on-nix/archive/fb1400959763420d1d1fb9db289a45b4d4649a48.tar.gz",
        "url_template": "https://github.com/<owner>/<repo>/archive/<rev>.tar.gz"
    }
}
