{
    "Lists": {
        "branch": "master",
        "description": "Primary Block Lists",
        "homepage": "",
        "owner": "blocklistproject",
        "repo": "Lists",
        "rev": "a3005f7a5c30db5e3ec677e7f94bc231ed0c4dc3",
        "sha256": "1fg32i0zqxk66yddhc93hd228mnr7ili63fd85alznr2wm4hb50c",
        "type": "tarball",
        "url": "https://github.com/blocklistproject/Lists/archive/a3005f7a5c30db5e3ec677e7f94bc231ed0c4dc3.tar.gz",
        "url_template": "https://github.com/<owner>/<repo>/archive/<rev>.tar.gz"
    },
    "Ultimate.Hosts.Blacklist": {
        "branch": "master",
        "description": "The Ultimate Unified Hosts file for protecting your network, computer, smartphones and Wi-Fi devices against millions of bad web sites. Protect your children and family from gaining access to bad web sites and protect your devices and pc from being infected with Malware or Ransomware.",
        "homepage": "",
        "owner": "Ultimate-Hosts-Blacklist",
        "repo": "Ultimate.Hosts.Blacklist",
        "rev": "4df224c76a5142cc375e85a99038256dd081ead4",
        "sha256": "0ybc3mszafiwb83hxnwi4vyzsjvpqk6lhbdjh6paq15ficj78vyj",
        "type": "tarball",
        "url": "https://github.com/Ultimate-Hosts-Blacklist/Ultimate.Hosts.Blacklist/archive/4df224c76a5142cc375e85a99038256dd081ead4.tar.gz",
        "url_template": "https://github.com/<owner>/<repo>/archive/<rev>.tar.gz"
    },
    "hosts": {
        "branch": "master",
        "description": "🔒 Consolidating and extending hosts files from several well-curated sources. Optionally pick extensions for porn, social media, and other categories.",
        "homepage": "",
        "owner": "StevenBlack",
        "repo": "hosts",
        "rev": "77fc3d574f782417daee7764908e67007602397e",
        "sha256": "0sf3h05xgsvwy88v3cmfhh7ln6skxc9cla4dx93w6ihq6i6h6224",
        "type": "tarball",
        "url": "https://github.com/StevenBlack/hosts/archive/77fc3d574f782417daee7764908e67007602397e.tar.gz",
        "url_template": "https://github.com/<owner>/<repo>/archive/<rev>.tar.gz"
    }
}
